zmq_client_server/__init__.py
zmq_client_server/zmq_client.py
zmq_client_server/zmq_server.py
zmq_client_server-0.0.1.dist-info/LICENSE
zmq_client_server-0.0.1.dist-info/METADATA
zmq_client_server-0.0.1.dist-info/WHEEL
zmq_client_server-0.0.1.dist-info/top_level.txt
zmq_client_server-0.0.1.dist-info/RECORD
