Metadata-Version: 2.1
Name: zmq_client_server
Version: 0.0.1
Summary: Python ZMQ Client/Server Wrapper
Home-page: https://github.com/perrytec/zmq_client_server
Author: perry
Author-email: noemail@example.com
Classifier: Programming Language :: Python :: 3
Classifier: Operating System :: OS Independent
Requires-Python: >=3.6
License-File: LICENSE
Requires-Dist: zmq
